lpif2dbxdriverack/__init__.py
lpif2dbxdriverack/lpif.py
lpif2dbxdriverack/lpif2dbxdriverack.py
lpif2dbxdriverack/py.typed
lpif2dbxdriverack-0.0.3.dist-info/LICENSE.txt
lpif2dbxdriverack-0.0.3.dist-info/METADATA
lpif2dbxdriverack-0.0.3.dist-info/WHEEL
lpif2dbxdriverack-0.0.3.dist-info/entry_points.txt
lpif2dbxdriverack-0.0.3.dist-info/top_level.txt
lpif2dbxdriverack-0.0.3.dist-info/RECORD
