Metadata-Version: 2.1
Name: lpif2dbxdriverack
Version: 0.0.3
Summary: Sends compatible Loudspeaker Processor Interchange Format (LPIF) file parameters to supported dbx DriveRack loudspeaker management systems
Author-email: Matt Kupferman <matt@kupferman.net>
Maintainer-email: Matt Kupferman <matt@kupferman.net>
License: MIT License
Project-URL: Homepage, https://github.com/mkupferman/lpif-dbxdriverack
Classifier: Programming Language :: Python :: 3
Classifier: License :: OSI Approved :: MIT License
Classifier: Operating System :: OS Independent
Classifier: Intended Audience :: End Users/Desktop
Classifier: Development Status :: 4 - Beta
Requires-Python: >=3.11
License-File: LICENSE.txt
Requires-Dist: dbxdriverack>=0.0.3
Requires-Dist: prompt_toolkit
Requires-Dist: Click
Provides-Extra: dev
Requires-Dist: black; extra == "dev"
Provides-Extra: validate
Requires-Dist: mypy; extra == "validate"
